{
  "default": "common",
  "entries": {

    "minecraft:protection": "common",
    "minecraft:fire_protection": "common",
    "minecraft:blast_protection": "common",
    "minecraft:projectile_protection": "common",


    "minecraft:thorns": "rare",
    "minecraft:respiration": "common",
    "minecraft:aqua_affinity": "uncommon",
    "minecraft:depth_strider": "rare",
    "minecraft:frost_walker": "rare",
    "minecraft:soul_speed": "epic",
    "minecraft:swift_sneak": "epic",
    "minecraft:feather_falling": "uncommon",
    "minecraft:swift": "uncommon",


    "minecraft:sharpness": "epic",
    "minecraft:smite": "common",
    "minecraft:bane_of_arthropods": "uncommon",
    "minecraft:knockback": "common",
    "minecraft:fire_aspect": "rare",
    "minecraft:looting": "uncommon",
    "minecraft:sweeping_edge": "uncommon",


    "runic:lightning_aspect": "legendary",
    "runic:poison_aspect": "epic",
    "runic:slowness_aspect": "rare",
    "runic:weakness_aspect": "epic",
    "runic:swiftstrike": "rare",
    "runic:bleeding_aspect": "epic",
    "runic:stunning_aspect": "legendary",
    "runic:soulbound": "legendary",
    "runic:air_jump": "rare",
    "runic:wither_aspect": "rare",
    "runic:mandela_aspect": "epic",
    "runic:vitality": "epic",
    "runic:leaping": "common",
    "runic:reach": "common",
    "runic:buzzing_aspect": "rare",



    "minecraft:efficiency": "common",
    "minecraft:silk_touch": "uncommon",
    "minecraft:fortune": "uncommon",
    "minecraft:smelting": "uncommon",


    "minecraft:unbreaking": "uncommon",
    "minecraft:mending": "legendary",


    "minecraft:vanishing_curse": "cursed",
    "minecraft:binding_curse": "cursed",
    "runic:curse_of_unluck": "cursed",
    "runic:toughness": "epic",


    "minecraft:power": "uncommon",
    "minecraft:punch": "common",
    "minecraft:flame": "rare",
    "minecraft:infinity": "legendary",


    "minecraft:multishot": "epic",
    "minecraft:piercing": "rare",
    "minecraft:quick_charge": "uncommon",


    "minecraft:impaling": "uncommon",
    "minecraft:riptide": "rare",
    "minecraft:loyalty": "legendary",
    "minecraft:channeling": "epic",


    "minecraft:luck_of_the_sea": "rare",
    "minecraft:lure": "uncommon",

    "minecraft:breach": "legendary",
    "minecraft:density": "legendary",
    "minecraft:wind_burst": "epic"
  }
}
